hades_rpc/__init__.py
hades_rpc/apps/__init__.py
hades_rpc/apps/endpoint.py
hades_rpc/apps/generator.py
hades_rpc/apps/hades.py
hades_rpc/apps/rpc.py
hades_rpc/generator/__init__.py
hades_rpc/generator/generator.py
hades_rpc/generator/nanopb.py
hades_rpc/rpc/__init__.py
hades_rpc/rpc/protocol.py
hades_rpc/rpc/rpc.py
hades_rpc/rpc/transports/simple_serial.py
hades_rpc/rpc/transports/transport.py
hades_rpc-0.1.6.dist-info/entry_points.txt
hades_rpc-0.1.6.dist-info/LICENSE
hades_rpc-0.1.6.dist-info/METADATA
hades_rpc-0.1.6.dist-info/WHEEL
hades_rpc-0.1.6.dist-info/RECORD
