Metadata-Version: 2.1
Name: hades-rpc
Version: 0.1.6
Summary: 
Author: Alejandro Lobo
Author-email: alobop@outlook.com
Requires-Python: >=3.9,<4.0
Classifier: Programming Language :: Python :: 3
Classifier: Programming Language :: Python :: 3.9
Classifier: Programming Language :: Python :: 3.10
Classifier: Programming Language :: Python :: 3.11
Classifier: Programming Language :: Python :: 3.12
Requires-Dist: attrs (>=23.2.0,<24.0.0)
Requires-Dist: grpcio (>=1.60.1,<2.0.0)
Requires-Dist: grpcio-tools (>=1.60.1,<2.0.0)
Requires-Dist: nanopb (>=0.4.8,<0.5.0)
Requires-Dist: pyserial (>=3.5,<4.0)
Requires-Dist: typer (>=0.9.0,<0.10.0)
